README.rst
setup.py
m2tools/__init__.py
m2tools/extension.py
m2tools/package.py
m2tools/patcher.py
m2tools.egg-info/PKG-INFO
m2tools.egg-info/SOURCES.txt
m2tools.egg-info/dependency_links.txt
m2tools.egg-info/requires.txt
m2tools.egg-info/top_level.txt