Metadata-Version: 1.1
Name: m2tools
Version: 0.1.2
Summary: Magento 2 python toolkit
Home-page: UNKNOWN
Author: Peter Samoilov
Author-email: xserv@gmail.com
License: MIT
Platform: UNKNOWN
Classifier: Topic :: Internet :: WWW/HTTP
Classifier: Topic :: Software Development :: Libraries :: Python Modules
Classifier: Intended Audience :: Developers
